hyper_compose-0.1.4.dist-info/DESCRIPTION.rst
hyper_compose-0.1.4.dist-info/METADATA
hyper_compose-0.1.4.dist-info/RECORD
hyper_compose-0.1.4.dist-info/WHEEL
hyper_compose-0.1.4.dist-info/entry_points.txt
hyper_compose-0.1.4.dist-info/metadata.json
hyper_compose-0.1.4.dist-info/pbr.json
hyper_compose-0.1.4.dist-info/top_level.txt
hypercompose/__init__.py
hypercompose/api.py
hypercompose/cmd.py
hypercompose/requests_aws4auth/__init__.py
hypercompose/requests_aws4auth/aws4auth.py
hypercompose/requests_aws4auth/aws4signingkey.py
hypercompose/requests_aws4auth/exceptions.py
hypercompose/requests_aws4auth/service_parameters.py
hypercompose/requests_aws4auth/six.py
hypercompose/requests_aws4auth/test/requests_aws4auth_test.py
