Metadata-Version: 2.0
Name: hyper-compose
Version: 0.1.4
Summary: docker-compose on hyper infra
Home-page: UNKNOWN
Author: Pierre Tardy
Author-email: tardyp@gmail.com
License: MIT
Keywords: docker
Requires-Dist: docker-compose
Requires-Dist: docker-py
